{
 "conventions": {
  "time_unit": "milliseconds for every field ending in _ms",
  "med_time_returns": "SECONDS (rtx4060_common.med_time); converted to ms here (*1e3)",
  "estimator_time_unit": "SECONDS (KTime.time_s); converted to ms here (*1e3)",
  "gain_definition": "gain = unfused_time / fused_time  (>1.0 => fusion FASTER), matches estimator '1.020x'",
  "measured_gain": "unfused_ms / best_fused_ms  (best over compiled/addmm/triton paths)",
  "estimated_gain": "est_unfused_ms / est_fused_ms  (fusion_time_estimator, rtx4060-measured profile)",
  "dtype": "bfloat16 for all measured tensors; fp32 accumulate",
  "hand_triton_numerics": "judged vs an fp32 reference: ok iff rel_max_vs_fp32 <= max(2 x eager path's own rel_max_vs_fp32, 5e-2). The hand kernel keeps gate/up in fp32 accumulators (MORE accurate than eager, which rounds gu to bf16 pre-silu), so allclose-vs-eager is the wrong criterion at large k",
  "gemm_drift_ratio": "bare-GEMM time re-measured at the END of the config / at the START; bounds DVFS+thermal drift across the config's timed region (~1.0 = clean)",
  "fused_verified": "True iff a Triton GEMM template folds the epilogue in AND no separate silu/mul/add elementwise kernel remains (raw kernel_evidence stored for re-judge)",
  "compiled_paths": "compiled_ms = plain max-autotune (cudagraphs ON; is_big_gpu()<68 SMs so inductor keeps the vendor GEMM + separate epilogue kernel on this GPU); unfused_compiled_nocg_ms / compiled_nocg_ms = max-autotune-no-cudagraphs unforced (for swiglu this is the BEST UNFUSED realization: vendor GEMM + one fused pointwise kernel, exactly the estimator's unfused model); compiled_forced_triton_ms = is_big_gpu patched + TRITON-only autotune backends + no-cudagraphs -> a genuine Triton GEMM template with the epilogue folded in (the object the task asks about); fused_verified_forced judges it",
  "measured_gain_verified": "best_unfused_ms / best VERIFIED-fused path (hand triton by construction; forced template iff fused_verified_forced; addmm iff addmm_fused_verified; compiled paths iff template- or vendor-fused per evidence). The A-vs-B verdict keys on THIS, not measured_gain",
  "addmm_fused_verified": "residual only: torch.addmm profile shows no separate add/elementwise kernel (Memcpy DtoD tolerated: beta-accumulate copy)",
  "compiled_cudagraph_input_copy_us": "GPU time of multi_tensor_apply static-input-copy kernels inside ONE compiled call (cudagraph deployment overhead, not fusion work); subtract from compiled_ms for a kernels-only fused-vs-unfused comparison",
  "timing": "median of 30 cuda-event samples, 15 warmup, per config"
 },
 "env": {
  "torch_version": "2.11.0+cu130",
  "cuda_version": "13.0",
  "triton_version": "3.6.0",
  "device_name": "NVIDIA GeForce RTX 4060 Laptop GPU",
  "sm_count": 24,
  "total_memory_gib": 7.9956,
  "smem_per_block_optin_bytes": 101376,
  "estimator_profile": "RTX 4060 Laptop (locked 1500/5501, measured)",
  "estimator_peak_tflops": 18.432,
  "estimator_bw_gbps": 170.0,
  "clocks_locked": false,
  "clocks_note": "WSL2 / no root: clocks NOT locked -> ClockSampler recorded per config",
  "smoke": false,
  "adjusted_profile": {
   "applied": {
    "clock_hz": 1529156128.3267167,
    "bw_bytes_per_s": 214842784962.90384
   },
   "source": "t2 adjusted_profile block",
   "check_peak_tflops": 18.790270504878695,
   "check_bw_gbs": 214.84278496290383
  }
 },
 "configs": [
  {
   "name": "swiglu_M2048_h1024",
   "kind": "swiglu",
   "dims": {
    "M": 2048,
    "hidden": 1024,
    "inter": 1024
   },
   "gemm_only_ms": 0.555519998073578,
   "unfused_ms": 0.45772799849510193,
   "gemm_only_repeat_ms": 0.47766399383544916,
   "gemm_drift_ratio": 0.8598502222996176,
   "eager_rel_max_vs_fp32": 0.015336453914642334,
   "unfused_compiled_nocg_ms": 0.5516959726810455,
   "best_unfused_ms": 0.45772799849510193,
   "fused_paths": {
    "compiled_ms": 0.5949440002441406,
    "compiled_forced_triton_ms": 0.532943993806839,
    "triton_ms": 0.520687997341156
   },
   "best_fused_ms": 0.520687997341156,
   "measured_gain": 0.879083060935621,
   "measured_gain_verified": 0.879083060935621,
   "est_unfused_ms": 0.5436917960784313,
   "est_fused_ms": 0.46967466666666663,
   "estimated_gain": 1.157592339261286,
   "fused_verified": false,
   "fused_verified_forced": false,
   "kernel_evidence": [
    {
     "name": "ampere_bf16_s1688gemm_bf16_128x128_ldg8_f2f_stages_32x1_nn",
     "count": 1,
     "total_us": 375.001,
     "avg_us": 375.001
    },
    {
     "name": "triton_poi_fused_mul_silu_slice_0",
     "count": 1,
     "total_us": 19.126,
     "avg_us": 19.126
    },
    {
     "name": "void at::native::(anonymous namespace)::multi_tensor_apply_kernel<at::native::(anonymous namespace)::TensorListMetadata<2>, at::native::(anonymous namespace)::UnaryOpFunctor<c10::BFloat16, 2, 1, 1>, at::native::Copy<c10::BFloat16, c10::BFloat16> >(at::native::(anonymous namespace)::TensorListMetadata<2>, at::native::(anonymous namespace)::UnaryOpFunctor<c10::BFloat16, 2, 1, 1>, at::native::Copy<c10::BFloat16, c10::BFloat16>)",
     "count": 1,
     "total_us": 16.339,
     "avg_us": 16.339
    }
   ],
   "fusion_evidence": {
    "n_kernels": 3,
    "dominant_kernel": "ampere_bf16_s1688gemm_bf16_128x128_ldg8_f2f_stages_32x1_nn",
    "dominant_frac_of_gpu_time": 0.9136,
    "triton_gemm_template_present": false,
    "separate_elementwise_kernels": [
     "triton_poi_fused_mul_silu_slice_0"
    ]
   },
   "nocg_kernel_evidence": [
    {
     "name": "ampere_bf16_s1688gemm_bf16_128x128_ldg8_f2f_stages_32x1_nn",
     "count": 1,
     "total_us": 427.795,
     "avg_us": 427.795
    },
    {
     "name": "triton_poi_fused_mul_silu_slice_0",
     "count": 1,
     "total_us": 21.768,
     "avg_us": 21.768
    }
   ],
   "nocg_fusion_evidence": {
    "n_kernels": 2,
    "dominant_kernel": "ampere_bf16_s1688gemm_bf16_128x128_ldg8_f2f_stages_32x1_nn",
    "dominant_frac_of_gpu_time": 0.9516,
    "triton_gemm_template_present": false,
    "separate_elementwise_kernels": [
     "triton_poi_fused_mul_silu_slice_0"
    ]
   },
   "forced_kernel_evidence": [
    {
     "name": "triton_tem_fused_mm_0",
     "count": 1,
     "total_us": 428.221,
     "avg_us": 428.221
    },
    {
     "name": "triton_poi_fused_mul_silu_slice_1",
     "count": 1,
     "total_us": 17.559,
     "avg_us": 17.559
    }
   ],
   "forced_fusion_evidence": {
    "n_kernels": 2,
    "dominant_kernel": "triton_tem_fused_mm_0",
    "dominant_frac_of_gpu_time": 0.9606,
    "triton_gemm_template_present": true,
    "separate_elementwise_kernels": [
     "triton_poi_fused_mul_silu_slice_1"
    ]
   },
   "numerics_ok": true,
   "max_abs_diff": 8.0,
   "nocg_numerics_ok": true,
   "nocg_max_abs_diff": 8.0,
   "forced_numerics_ok": true,
   "forced_max_abs_diff": 8.0,
   "compiled_over_gemm_ratio": 1.0709677460888474,
   "nocg_over_gemm_ratio": 0.9931163137136496,
   "forced_over_gemm_ratio": 0.9593605912567906,
   "triton_over_gemm_ratio": 0.9372983855608947,
   "compiled_cudagraph_input_copy_us": 16.339,
   "triton_info": {
    "numerics_ok": true,
    "rel_max_vs_fp32": 0.0038884361274540424,
    "eager_rel_max_vs_fp32": 0.015336453914642334,
    "rel_tol": 0.05,
    "max_abs_diff_vs_eager": 64.0,
    "config": "BM64 BN64 BK32 w4 s2 (tuned over 6 candidates)"
   },
   "compile_error": null,
   "nocg_error": null,
   "forced_error": null,
   "clocks": {
    "gr_mhz": {
     "median": 1725.0,
     "min": 210.0,
     "max": 2070.0
    },
    "mem_mhz": {
     "median": 7001.0,
     "min": 810.0,
     "max": 7001.0
    },
    "temp_c": {
     "median": 68.0,
     "min": 64.0,
     "max": 72.0
    },
    "power_w": {
     "median": 20.83,
     "min": 9.32,
     "max": 34.85
    },
    "n_samples": 9
   },
   "est_unfused_ms_adj": 0.5192874682834372,
   "est_fused_ms_adj": 0.46071946935262537,
   "estimated_gain_adj": 1.1271229084655527
  },
  {
   "name": "swiglu_M2048_h2048",
   "kind": "swiglu",
   "dims": {
    "M": 2048,
    "hidden": 2048,
    "inter": 2048
   },
   "gemm_only_ms": 1.9988799691200259,
   "unfused_ms": 2.013439893722534,
   "gemm_only_repeat_ms": 1.7420960068702698,
   "gemm_drift_ratio": 0.8715360770948137,
   "eager_rel_max_vs_fp32": 0.015834730118513107,
   "unfused_compiled_nocg_ms": 1.9585759639739992,
   "best_unfused_ms": 1.9585759639739992,
   "fused_paths": {
    "compiled_ms": 2.205295920372009,
    "compiled_forced_triton_ms": 2.48088002204895,
    "triton_ms": 1.8730880022048948
   },
   "best_fused_ms": 1.8730880022048948,
   "measured_gain": 1.0749307514395612,
   "measured_gain_verified": 1.0456401203085348,
   "est_unfused_ms": 2.026732925490196,
   "est_fused_ms": 1.8786986666666665,
   "estimated_gain": 1.078796169630643,
   "fused_verified": false,
   "fused_verified_forced": false,
   "kernel_evidence": [
    {
     "name": "ampere_bf16_s1688gemm_bf16_128x128_ldg8_f2f_stages_32x1_nn",
     "count": 1,
     "total_us": 1680.734,
     "avg_us": 1680.734
    },
    {
     "name": "void at::native::(anonymous namespace)::multi_tensor_apply_kernel<at::native::(anonymous namespace)::TensorListMetadata<2>, at::native::(anonymous namespace)::UnaryOpFunctor<c10::BFloat16, 2, 1, 1>, at::native::Copy<c10::BFloat16, c10::BFloat16> >(at::native::(anonymous namespace)::TensorListMetadata<2>, at::native::(anonymous namespace)::UnaryOpFunctor<c10::BFloat16, 2, 1, 1>, at::native::Copy<c10::BFloat16, c10::BFloat16>)",
     "count": 1,
     "total_us": 275.222,
     "avg_us": 275.222
    },
    {
     "name": "triton_poi_fused_mul_silu_slice_0",
     "count": 1,
     "total_us": 137.642,
     "avg_us": 137.642
    }
   ],
   "fusion_evidence": {
    "n_kernels": 3,
    "dominant_kernel": "ampere_bf16_s1688gemm_bf16_128x128_ldg8_f2f_stages_32x1_nn",
    "dominant_frac_of_gpu_time": 0.8028,
    "triton_gemm_template_present": false,
    "separate_elementwise_kernels": [
     "triton_poi_fused_mul_silu_slice_0"
    ]
   },
   "nocg_kernel_evidence": [
    {
     "name": "ampere_bf16_s1688gemm_bf16_128x128_ldg8_f2f_stages_32x1_nn",
     "count": 1,
     "total_us": 1739.927,
     "avg_us": 1739.927
    },
    {
     "name": "triton_poi_fused_mul_silu_slice_0",
     "count": 1,
     "total_us": 76.698,
     "avg_us": 76.698
    }
   ],
   "nocg_fusion_evidence": {
    "n_kernels": 2,
    "dominant_kernel": "ampere_bf16_s1688gemm_bf16_128x128_ldg8_f2f_stages_32x1_nn",
    "dominant_frac_of_gpu_time": 0.9578,
    "triton_gemm_template_present": false,
    "separate_elementwise_kernels": [
     "triton_poi_fused_mul_silu_slice_0"
    ]
   },
   "forced_kernel_evidence": [
    {
     "name": "triton_tem_fused_mm_0",
     "count": 1,
     "total_us": 2374.574,
     "avg_us": 2374.574
    },
    {
     "name": "triton_poi_fused_mul_silu_slice_1",
     "count": 1,
     "total_us": 80.406,
     "avg_us": 80.406
    }
   ],
   "forced_fusion_evidence": {
    "n_kernels": 2,
    "dominant_kernel": "triton_tem_fused_mm_0",
    "dominant_frac_of_gpu_time": 0.9672,
    "triton_gemm_template_present": true,
    "separate_elementwise_kernels": [
     "triton_poi_fused_mul_silu_slice_1"
    ]
   },
   "numerics_ok": true,
   "max_abs_diff": 8.0,
   "nocg_numerics_ok": true,
   "nocg_max_abs_diff": 8.0,
   "forced_numerics_ok": true,
   "forced_max_abs_diff": 8.0,
   "compiled_over_gemm_ratio": 1.1032658060718143,
   "nocg_over_gemm_ratio": 0.9798367056708414,
   "forced_over_gemm_ratio": 1.2411350658244462,
   "triton_over_gemm_ratio": 0.9370687740842644,
   "compiled_cudagraph_input_copy_us": 275.222,
   "triton_info": {
    "numerics_ok": true,
    "rel_max_vs_fp32": 0.004011092241853476,
    "eager_rel_max_vs_fp32": 0.015834730118513107,
    "rel_tol": 0.05,
    "max_abs_diff_vs_eager": 128.0,
    "config": "BM64 BN64 BK64 w4 s3 (tuned over 6 candidates)"
   },
   "compile_error": null,
   "nocg_error": null,
   "forced_error": null,
   "clocks": {
    "gr_mhz": {
     "median": 1695.0,
     "min": 405.0,
     "max": 2070.0
    },
    "mem_mhz": {
     "median": 5501.0,
     "min": 5501.0,
     "max": 7001.0
    },
    "temp_c": {
     "median": 72.0,
     "min": 67.0,
     "max": 74.0
    },
    "power_w": {
     "median": 34.02,
     "min": 10.36,
     "max": 36.68
    },
    "n_samples": 9
   },
   "est_unfused_ms_adj": 1.9600138752721252,
   "est_fused_ms_adj": 1.8428778774105015,
   "estimated_gain_adj": 1.0635614542327765
  },
  {
   "name": "swiglu_M2048_h4096",
   "kind": "swiglu",
   "dims": {
    "M": 2048,
    "hidden": 4096,
    "inter": 4096
   },
   "gemm_only_ms": 7.273967981338501,
   "unfused_ms": 7.683791875839233,
   "gemm_only_repeat_ms": 7.285520076751709,
   "gemm_drift_ratio": 1.0015881421863342,
   "eager_rel_max_vs_fp32": 0.018329396843910217,
   "unfused_compiled_nocg_ms": 7.604608058929443,
   "best_unfused_ms": 7.604608058929443,
   "fused_paths": {
    "compiled_ms": 8.727968215942383,
    "compiled_forced_triton_ms": 8.532512187957764,
    "triton_ms": 7.203376054763794
   },
   "best_fused_ms": 7.203376054763794,
   "measured_gain": 1.0666931474107515,
   "measured_gain_verified": 1.0557005494528227,
   "est_unfused_ms": 7.767172517647059,
   "est_fused_ms": 7.471104,
   "estimated_gain": 1.0396284829721363,
   "fused_verified": false,
   "fused_verified_forced": false,
   "kernel_evidence": [
    {
     "name": "ampere_bf16_s1688gemm_bf16_128x128_ldg8_f2f_stages_32x1_nn",
     "count": 1,
     "total_us": 7962.595,
     "avg_us": 7962.595
    },
    {
     "name": "void at::native::(anonymous namespace)::multi_tensor_apply_kernel<at::native::(anonymous namespace)::TensorListMetadata<2>, at::native::(anonymous namespace)::UnaryOpFunctor<c10::BFloat16, 2, 1, 1>, at::native::Copy<c10::BFloat16, c10::BFloat16> >(at::native::(anonymous namespace)::TensorListMetadata<2>, at::native::(anonymous namespace)::UnaryOpFunctor<c10::BFloat16, 2, 1, 1>, at::native::Copy<c10::BFloat16, c10::BFloat16>)",
     "count": 2,
     "total_us": 1207.826,
     "avg_us": 603.913
    },
    {
     "name": "triton_poi_fused_mul_silu_slice_0",
     "count": 1,
     "total_us": 238.693,
     "avg_us": 238.693
    }
   ],
   "fusion_evidence": {
    "n_kernels": 3,
    "dominant_kernel": "ampere_bf16_s1688gemm_bf16_128x128_ldg8_f2f_stages_32x1_nn",
    "dominant_frac_of_gpu_time": 0.8463,
    "triton_gemm_template_present": false,
    "separate_elementwise_kernels": [
     "triton_poi_fused_mul_silu_slice_0"
    ]
   },
   "nocg_kernel_evidence": [
    {
     "name": "ampere_bf16_s1688gemm_bf16_128x128_ldg8_f2f_stages_32x1_nn",
     "count": 1,
     "total_us": 7073.66,
     "avg_us": 7073.66
    },
    {
     "name": "triton_poi_fused_mul_silu_slice_0",
     "count": 1,
     "total_us": 251.57,
     "avg_us": 251.57
    }
   ],
   "nocg_fusion_evidence": {
    "n_kernels": 2,
    "dominant_kernel": "ampere_bf16_s1688gemm_bf16_128x128_ldg8_f2f_stages_32x1_nn",
    "dominant_frac_of_gpu_time": 0.9657,
    "triton_gemm_template_present": false,
    "separate_elementwise_kernels": [
     "triton_poi_fused_mul_silu_slice_0"
    ]
   },
   "forced_kernel_evidence": [
    {
     "name": "triton_tem_fused_mm_0",
     "count": 1,
     "total_us": 7978.749,
     "avg_us": 7978.749
    },
    {
     "name": "triton_poi_fused_mul_silu_slice_1",
     "count": 1,
     "total_us": 251.357,
     "avg_us": 251.357
    }
   ],
   "forced_fusion_evidence": {
    "n_kernels": 2,
    "dominant_kernel": "triton_tem_fused_mm_0",
    "dominant_frac_of_gpu_time": 0.9695,
    "triton_gemm_template_present": true,
    "separate_elementwise_kernels": [
     "triton_poi_fused_mul_silu_slice_1"
    ]
   },
   "numerics_ok": true,
   "max_abs_diff": 16.0,
   "nocg_numerics_ok": true,
   "nocg_max_abs_diff": 16.0,
   "forced_numerics_ok": true,
   "forced_max_abs_diff": 16.0,
   "compiled_over_gemm_ratio": 1.199890931378052,
   "nocg_over_gemm_ratio": 1.045455256118697,
   "forced_over_gemm_ratio": 1.1730203115889541,
   "triton_over_gemm_ratio": 0.9902952656987477,
   "compiled_cudagraph_input_copy_us": 1207.826,
   "triton_info": {
    "numerics_ok": true,
    "rel_max_vs_fp32": 0.018092412501573563,
    "eager_rel_max_vs_fp32": 0.018329396843910217,
    "rel_tol": 0.05,
    "max_abs_diff_vs_eager": 256.0,
    "config": "BM128 BN64 BK32 w4 s3 (tuned over 6 candidates)"
   },
   "compile_error": null,
   "nocg_error": null,
   "forced_error": null,
   "clocks": {
    "gr_mhz": {
     "median": 1605.0,
     "min": 375.0,
     "max": 2070.0
    },
    "mem_mhz": {
     "median": 5501.0,
     "min": 5501.0,
     "max": 7001.0
    },
    "temp_c": {
     "median": 74.0,
     "min": 68.0,
     "max": 74.0
    },
    "power_w": {
     "median": 33.32,
     "min": 10.23,
     "max": 36.33
    },
    "n_samples": 13
   },
   "est_unfused_ms_adj": 7.562925880309194,
   "est_fused_ms_adj": 7.328653884585947,
   "estimated_gain_adj": 1.0319665793217472
  },
  {
   "name": "swiglu_M8192_h1024",
   "kind": "swiglu",
   "dims": {
    "M": 8192,
    "hidden": 1024,
    "inter": 1024
   },
   "gemm_only_ms": 1.968464016914368,
   "unfused_ms": 2.3641120195388794,
   "gemm_only_repeat_ms": 1.9956640005111694,
   "gemm_drift_ratio": 1.01381787188543,
   "eager_rel_max_vs_fp32": 0.016418252140283585,
   "unfused_compiled_nocg_ms": 2.1003839969635014,
   "best_unfused_ms": 2.1003839969635014,
   "fused_paths": {
    "compiled_ms": 2.327567934989929,
    "compiled_forced_triton_ms": 3.13702392578125,
    "triton_ms": 1.9558879733085635
   },
   "best_fused_ms": 1.9558879733085635,
   "measured_gain": 1.208715453953003,
   "measured_gain_verified": 1.0738774539374614,
   "est_unfused_ms": 2.1638445176470587,
   "est_fused_ms": 1.867776,
   "estimated_gain": 1.1585139318885447,
   "fused_verified": false,
   "fused_verified_forced": false,
   "kernel_evidence": [
    {
     "name": "ampere_bf16_s1688gemm_bf16_128x128_ldg8_f2f_stages_32x1_nn",
     "count": 1,
     "total_us": 1707.005,
     "avg_us": 1707.005
    },
    {
     "name": "triton_poi_fused_mul_silu_slice_0",
     "count": 1,
     "total_us": 308.283,
     "avg_us": 308.283
    },
    {
     "name": "void at::native::(anonymous namespace)::multi_tensor_apply_kernel<at::native::(anonymous namespace)::TensorListMetadata<2>, at::native::(anonymous namespace)::UnaryOpFunctor<c10::BFloat16, 2, 1, 1>, at::native::Copy<c10::BFloat16, c10::BFloat16> >(at::native::(anonymous namespace)::TensorListMetadata<2>, at::native::(anonymous namespace)::UnaryOpFunctor<c10::BFloat16, 2, 1, 1>, at::native::Copy<c10::BFloat16, c10::BFloat16>)",
     "count": 1,
     "total_us": 229.02,
     "avg_us": 229.02
    }
   ],
   "fusion_evidence": {
    "n_kernels": 3,
    "dominant_kernel": "ampere_bf16_s1688gemm_bf16_128x128_ldg8_f2f_stages_32x1_nn",
    "dominant_frac_of_gpu_time": 0.7606,
    "triton_gemm_template_present": false,
    "separate_elementwise_kernels": [
     "triton_poi_fused_mul_silu_slice_0"
    ]
   },
   "nocg_kernel_evidence": [
    {
     "name": "ampere_bf16_s1688gemm_bf16_128x128_ldg8_f2f_stages_32x1_nn",
     "count": 1,
     "total_us": 1764.183,
     "avg_us": 1764.183
    },
    {
     "name": "triton_poi_fused_mul_silu_slice_0",
     "count": 1,
     "total_us": 232.201,
     "avg_us": 232.201
    }
   ],
   "nocg_fusion_evidence": {
    "n_kernels": 2,
    "dominant_kernel": "ampere_bf16_s1688gemm_bf16_128x128_ldg8_f2f_stages_32x1_nn",
    "dominant_frac_of_gpu_time": 0.8837,
    "triton_gemm_template_present": false,
    "separate_elementwise_kernels": [
     "triton_poi_fused_mul_silu_slice_0"
    ]
   },
   "forced_kernel_evidence": [
    {
     "name": "triton_tem_fused_mm_0",
     "count": 1,
     "total_us": 2798.377,
     "avg_us": 2798.377
    },
    {
     "name": "triton_poi_fused_mul_silu_slice_1",
     "count": 1,
     "total_us": 217.641,
     "avg_us": 217.641
    }
   ],
   "forced_fusion_evidence": {
    "n_kernels": 2,
    "dominant_kernel": "triton_tem_fused_mm_0",
    "dominant_frac_of_gpu_time": 0.9278,
    "triton_gemm_template_present": true,
    "separate_elementwise_kernels": [
     "triton_poi_fused_mul_silu_slice_1"
    ]
   },
   "numerics_ok": true,
   "max_abs_diff": 8.0,
   "nocg_numerics_ok": true,
   "nocg_max_abs_diff": 8.0,
   "forced_numerics_ok": true,
   "forced_max_abs_diff": 8.0,
   "compiled_over_gemm_ratio": 1.182428489924072,
   "nocg_over_gemm_ratio": 1.0670167089241094,
   "forced_over_gemm_ratio": 1.5936404723814246,
   "triton_over_gemm_ratio": 0.9936112402879897,
   "compiled_cudagraph_input_copy_us": 229.02,
   "triton_info": {
    "numerics_ok": true,
    "rel_max_vs_fp32": 0.0038884440436959267,
    "eager_rel_max_vs_fp32": 0.016418252140283585,
    "rel_tol": 0.05,
    "max_abs_diff_vs_eager": 64.0,
    "config": "BM128 BN64 BK32 w4 s3 (tuned over 6 candidates)"
   },
   "compile_error": null,
   "nocg_error": null,
   "forced_error": null,
   "clocks": {
    "gr_mhz": {
     "median": 1530.0,
     "min": 360.0,
     "max": 2070.0
    },
    "mem_mhz": {
     "median": 7001.0,
     "min": 5501.0,
     "max": 7001.0
    },
    "temp_c": {
     "median": 74.0,
     "min": 70.0,
     "max": 74.0
    },
    "power_w": {
     "median": 31.8,
     "min": 10.69,
     "max": 36.28
    },
    "n_samples": 9
   },
   "est_unfused_ms_adj": 2.0664354668697342,
   "est_fused_ms_adj": 1.8321634711464867,
   "estimated_gain_adj": 1.127866317286989
  },
  {
   "name": "swiglu_M8192_h2048",
   "kind": "swiglu",
   "dims": {
    "M": 8192,
    "hidden": 2048,
    "inter": 2048
   },
   "gemm_only_ms": 6.956480026245117,
   "unfused_ms": 8.312352180480959,
   "gemm_only_repeat_ms": 9.358288288116455,
   "gemm_drift_ratio": 1.34526200791347,
   "eager_rel_max_vs_fp32": 0.01771337352693081,
   "unfused_compiled_nocg_ms": 8.376912117004395,
   "best_unfused_ms": 8.312352180480959,
   "fused_paths": {
    "compiled_ms": 8.188464164733885,
    "compiled_forced_triton_ms": 9.152368068695068,
    "triton_ms": 9.411808013916016
   },
   "best_fused_ms": 8.188464164733885,
   "measured_gain": 1.015129579033958,
   "measured_gain_verified": 0.8831833552268136,
   "est_unfused_ms": 8.063241035294118,
   "est_fused_ms": 7.471104,
   "estimated_gain": 1.0792569659442723,
   "fused_verified": false,
   "fused_verified_forced": false,
   "kernel_evidence": [
    {
     "name": "ampere_bf16_s1688gemm_bf16_128x128_ldg8_f2f_stages_32x1_nn",
     "count": 1,
     "total_us": 7167.631,
     "avg_us": 7167.631
    },
    {
     "name": "void at::native::(anonymous namespace)::multi_tensor_apply_kernel<at::native::(anonymous namespace)::TensorListMetadata<2>, at::native::(anonymous namespace)::UnaryOpFunctor<c10::BFloat16, 2, 1, 1>, at::native::Copy<c10::BFloat16, c10::BFloat16> >(at::native::(anonymous namespace)::TensorListMetadata<2>, at::native::(anonymous namespace)::UnaryOpFunctor<c10::BFloat16, 2, 1, 1>, at::native::Copy<c10::BFloat16, c10::BFloat16>)",
     "count": 2,
     "total_us": 497.887,
     "avg_us": 248.943
    },
    {
     "name": "triton_poi_fused_mul_silu_slice_0",
     "count": 1,
     "total_us": 482.112,
     "avg_us": 482.112
    }
   ],
   "fusion_evidence": {
    "n_kernels": 3,
    "dominant_kernel": "ampere_bf16_s1688gemm_bf16_128x128_ldg8_f2f_stages_32x1_nn",
    "dominant_frac_of_gpu_time": 0.8797,
    "triton_gemm_template_present": false,
    "separate_elementwise_kernels": [
     "triton_poi_fused_mul_silu_slice_0"
    ]
   },
   "nocg_kernel_evidence": [
    {
     "name": "ampere_bf16_s1688gemm_bf16_128x128_ldg8_f2f_stages_32x1_nn",
     "count": 1,
     "total_us": 7833.742,
     "avg_us": 7833.742
    },
    {
     "name": "triton_poi_fused_mul_silu_slice_0",
     "count": 1,
     "total_us": 531.048,
     "avg_us": 531.048
    }
   ],
   "nocg_fusion_evidence": {
    "n_kernels": 2,
    "dominant_kernel": "ampere_bf16_s1688gemm_bf16_128x128_ldg8_f2f_stages_32x1_nn",
    "dominant_frac_of_gpu_time": 0.9365,
    "triton_gemm_template_present": false,
    "separate_elementwise_kernels": [
     "triton_poi_fused_mul_silu_slice_0"
    ]
   },
   "forced_kernel_evidence": [
    {
     "name": "triton_tem_fused_mm_0",
     "count": 1,
     "total_us": 8487.162,
     "avg_us": 8487.162
    },
    {
     "name": "triton_poi_fused_mul_silu_slice_1",
     "count": 1,
     "total_us": 566.745,
     "avg_us": 566.745
    }
   ],
   "forced_fusion_evidence": {
    "n_kernels": 2,
    "dominant_kernel": "triton_tem_fused_mm_0",
    "dominant_frac_of_gpu_time": 0.9374,
    "triton_gemm_template_present": true,
    "separate_elementwise_kernels": [
     "triton_poi_fused_mul_silu_slice_1"
    ]
   },
   "numerics_ok": true,
   "max_abs_diff": 16.0,
   "nocg_numerics_ok": true,
   "nocg_max_abs_diff": 16.0,
   "forced_numerics_ok": true,
   "forced_max_abs_diff": 16.0,
   "compiled_over_gemm_ratio": 1.1770987818323044,
   "nocg_over_gemm_ratio": 1.204188337406322,
   "forced_over_gemm_ratio": 1.315660798876069,
   "triton_over_gemm_ratio": 1.3529555146291716,
   "compiled_cudagraph_input_copy_us": 497.887,
   "triton_info": {
    "numerics_ok": true,
    "rel_max_vs_fp32": 0.004674677737057209,
    "eager_rel_max_vs_fp32": 0.01771337352693081,
    "rel_tol": 0.05,
    "max_abs_diff_vs_eager": 128.0,
    "config": "BM64 BN128 BK32 w4 s3 (tuned over 6 candidates)"
   },
   "compile_error": null,
   "nocg_error": null,
   "forced_error": null,
   "clocks": {
    "gr_mhz": {
     "median": 1455.0,
     "min": 330.0,
     "max": 1935.0
    },
    "mem_mhz": {
     "median": 7001.0,
     "min": 5501.0,
     "max": 7001.0
    },
    "temp_c": {
     "median": 74.0,
     "min": 70.0,
     "max": 74.0
    },
    "power_w": {
     "median": 30.81,
     "min": 10.3,
     "max": 36.73
    },
    "n_samples": 13
   },
   "est_unfused_ms_adj": 7.797197876032443,
   "est_fused_ms_adj": 7.328653884585947,
   "estimated_gain_adj": 1.0639331586434946
  },
  {
   "name": "swiglu_M8192_h4096",
   "kind": "swiglu",
   "dims": {
    "M": 8192,
    "hidden": 4096,
    "inter": 4096
   },
   "gemm_only_ms": 32.12318420410156,
   "unfused_ms": 34.54308891296387,
   "gemm_only_repeat_ms": 39.645792007446296,
   "gemm_drift_ratio": 1.2341800163877972,
   "eager_rel_max_vs_fp32": 0.021990027278661728,
   "unfused_compiled_nocg_ms": 38.997055053710945,
   "best_unfused_ms": 34.54308891296387,
   "fused_paths": {
    "compiled_ms": 42.12212944030762,
    "compiled_forced_triton_ms": 41.243728637695305,
    "triton_ms": 41.49528121948243
   },
   "best_fused_ms": 41.243728637695305,
   "measured_gain": 0.8375355491354074,
   "measured_gain_verified": 0.8324582433904691,
   "est_unfused_ms": 31.068690070588236,
   "est_fused_ms": 29.84072533333333,
   "estimated_gain": 1.0411506330204117,
   "fused_verified": false,
   "fused_verified_forced": false,
   "kernel_evidence": [
    {
     "name": "ampere_bf16_s1688gemm_bf16_128x128_ldg8_f2f_stages_32x1_nn",
     "count": 1,
     "total_us": 33384.793,
     "avg_us": 33384.793
    },
    {
     "name": "void at::native::(anonymous namespace)::multi_tensor_apply_kernel<at::native::(anonymous namespace)::TensorListMetadata<2>, at::native::(anonymous namespace)::UnaryOpFunctor<c10::BFloat16, 2, 1, 1>, at::native::Copy<c10::BFloat16, c10::BFloat16> >(at::native::(anonymous namespace)::TensorListMetadata<2>, at::native::(anonymous namespace)::UnaryOpFunctor<c10::BFloat16, 2, 1, 1>, at::native::Copy<c10::BFloat16, c10::BFloat16>)",
     "count": 4,
     "total_us": 1392.753,
     "avg_us": 348.188
    },
    {
     "name": "triton_poi_fused_mul_silu_slice_0",
     "count": 1,
     "total_us": 1065.403,
     "avg_us": 1065.403
    }
   ],
   "fusion_evidence": {
    "n_kernels": 3,
    "dominant_kernel": "ampere_bf16_s1688gemm_bf16_128x128_ldg8_f2f_stages_32x1_nn",
    "dominant_frac_of_gpu_time": 0.9314,
    "triton_gemm_template_present": false,
    "separate_elementwise_kernels": [
     "triton_poi_fused_mul_silu_slice_0"
    ]
   },
   "nocg_kernel_evidence": [
    {
     "name": "ampere_bf16_s1688gemm_bf16_128x128_ldg8_f2f_stages_32x1_nn",
     "count": 1,
     "total_us": 37198.504,
     "avg_us": 37198.504
    },
    {
     "name": "triton_poi_fused_mul_silu_slice_0",
     "count": 1,
     "total_us": 1146.586,
     "avg_us": 1146.586
    }
   ],
   "nocg_fusion_evidence": {
    "n_kernels": 2,
    "dominant_kernel": "ampere_bf16_s1688gemm_bf16_128x128_ldg8_f2f_stages_32x1_nn",
    "dominant_frac_of_gpu_time": 0.9701,
    "triton_gemm_template_present": false,
    "separate_elementwise_kernels": [
     "triton_poi_fused_mul_silu_slice_0"
    ]
   },
   "forced_kernel_evidence": [
    {
     "name": "triton_tem_fused_mm_0",
     "count": 1,
     "total_us": 40055.621,
     "avg_us": 40055.621
    },
    {
     "name": "triton_poi_fused_mul_silu_slice_1",
     "count": 1,
     "total_us": 894.229,
     "avg_us": 894.229
    }
   ],
   "forced_fusion_evidence": {
    "n_kernels": 2,
    "dominant_kernel": "triton_tem_fused_mm_0",
    "dominant_frac_of_gpu_time": 0.9782,
    "triton_gemm_template_present": true,
    "separate_elementwise_kernels": [
     "triton_poi_fused_mul_silu_slice_1"
    ]
   },
   "numerics_ok": true,
   "max_abs_diff": 16.0,
   "nocg_numerics_ok": true,
   "nocg_max_abs_diff": 16.0,
   "forced_numerics_ok": true,
   "forced_max_abs_diff": 16.0,
   "compiled_over_gemm_ratio": 1.3112688073721337,
   "nocg_over_gemm_ratio": 1.2139847284732037,
   "forced_over_gemm_ratio": 1.2839240461233357,
   "triton_over_gemm_ratio": 1.2917549193079128,
   "compiled_cudagraph_input_copy_us": 1392.753,
   "triton_info": {
    "numerics_ok": true,
    "rel_max_vs_fp32": 0.021990027278661728,
    "eager_rel_max_vs_fp32": 0.021990027278661728,
    "rel_tol": 0.05,
    "max_abs_diff_vs_eager": 256.0,
    "config": "BM64 BN128 BK32 w4 s3 (tuned over 6 candidates)"
   },
   "compile_error": null,
   "nocg_error": null,
   "forced_error": null,
   "clocks": {
    "gr_mhz": {
     "median": 1140.0,
     "min": 360.0,
     "max": 2070.0
    },
    "mem_mhz": {
     "median": 6251.0,
     "min": 5501.0,
     "max": 8001.0
    },
    "temp_c": {
     "median": 74.0,
     "min": 70.0,
     "max": 75.0
    },
    "power_w": {
     "median": 28.29,
     "min": 10.74,
     "max": 34.38
    },
    "n_samples": 52
   },
   "est_unfused_ms_adj": 30.251703521236777,
   "est_fused_ms_adj": 29.27175791328773,
   "estimated_gain_adj": 1.0334775113558932
  },
  {
   "name": "residual_M2048",
   "kind": "residual",
   "dims": {
    "M": 2048,
    "n": 16384,
    "k": 6144
   },
   "gemm_only_ms": 26.36569595336914,
   "unfused_ms": 30.87504005432129,
   "gemm_only_repeat_ms": 29.943168640136722,
   "gemm_drift_ratio": 1.1356866396811511,
   "best_unfused_ms": 30.87504005432129,
   "fused_paths": {
    "addmm_ms": 30.50835132598877,
    "compiled_ms": 33.85444641113282,
    "compiled_nocg_ms": 30.660767555236816,
    "compiled_forced_triton_ms": 29.809184074401855
   },
   "best_fused_ms": 29.809184074401855,
   "measured_gain": 1.0357559595478738,
   "measured_gain_verified": 1.0357559595478738,
   "est_unfused_ms": 23.597586070588235,
   "est_fused_ms": 22.413312,
   "estimated_gain": 1.0528379772961816,
   "fused_verified": false,
   "fused_verified_forced": true,
   "addmm_fused_verified": true,
   "addmm_kernel_evidence": [
    {
     "name": "ampere_bf16_s1688gemm_bf16_128x128_ldg8_f2f_stages_32x1_nn",
     "count": 1,
     "total_us": 29824.388,
     "avg_us": 29824.388
    },
    {
     "name": "Memcpy DtoD (Device -> Device)",
     "count": 1,
     "total_us": 567.777,
     "avg_us": 567.777
    }
   ],
   "addmm_separate_kernels": [],
   "kernel_evidence": [
    {
     "name": "ampere_bf16_s1688gemm_bf16_128x128_ldg8_f2f_stages_32x1_nn",
     "count": 1,
     "total_us": 29825.716,
     "avg_us": 29825.716
    },
    {
     "name": "void at::native::(anonymous namespace)::multi_tensor_apply_kernel<at::native::(anonymous namespace)::TensorListMetadata<2>, at::native::(anonymous namespace)::UnaryOpFunctor<c10::BFloat16, 2, 1, 1>, at::native::Copy<c10::BFloat16, c10::BFloat16> >(at::native::(anonymous namespace)::TensorListMetadata<2>, at::native::(anonymous namespace)::UnaryOpFunctor<c10::BFloat16, 2, 1, 1>, at::native::Copy<c10::BFloat16, c10::BFloat16>)",
     "count": 7,
     "total_us": 3115.476,
     "avg_us": 445.068
    },
    {
     "name": "Memcpy DtoD (Device -> Device)",
     "count": 1,
     "total_us": 675.639,
     "avg_us": 675.639
    }
   ],
   "fusion_evidence": {
    "n_kernels": 3,
    "dominant_kernel": "ampere_bf16_s1688gemm_bf16_128x128_ldg8_f2f_stages_32x1_nn",
    "dominant_frac_of_gpu_time": 0.8872,
    "triton_gemm_template_present": false,
    "separate_elementwise_kernels": [],
    "vendor_fused_ok": true,
    "vendor_separate_kernels": []
   },
   "nocg_kernel_evidence": [
    {
     "name": "ampere_bf16_s1688gemm_bf16_128x128_ldg8_f2f_stages_32x1_nn",
     "count": 1,
     "total_us": 29828.626,
     "avg_us": 29828.626
    },
    {
     "name": "Memcpy DtoD (Device -> Device)",
     "count": 1,
     "total_us": 571.942,
     "avg_us": 571.942
    }
   ],
   "nocg_fusion_evidence": {
    "n_kernels": 2,
    "dominant_kernel": "ampere_bf16_s1688gemm_bf16_128x128_ldg8_f2f_stages_32x1_nn",
    "dominant_frac_of_gpu_time": 0.9812,
    "triton_gemm_template_present": false,
    "separate_elementwise_kernels": [],
    "vendor_fused_ok": true,
    "vendor_separate_kernels": []
   },
   "forced_kernel_evidence": [
    {
     "name": "triton_tem_fused_addmm_0",
     "count": 1,
     "total_us": 29757.615,
     "avg_us": 29757.615
    }
   ],
   "forced_fusion_evidence": {
    "n_kernels": 1,
    "dominant_kernel": "triton_tem_fused_addmm_0",
    "dominant_frac_of_gpu_time": 1.0,
    "triton_gemm_template_present": true,
    "separate_elementwise_kernels": [],
    "vendor_fused_ok": true,
    "vendor_separate_kernels": []
   },
   "numerics_ok": false,
   "max_abs_diff": 2.0,
   "nocg_numerics_ok": false,
   "nocg_max_abs_diff": 2.0,
   "forced_numerics_ok": false,
   "forced_max_abs_diff": 2.0,
   "addmm_numerics_ok": false,
   "addmm_max_abs_diff": 2.0,
   "compiled_over_gemm_ratio": 1.2840338624479484,
   "nocg_over_gemm_ratio": 1.1629037826069155,
   "forced_over_gemm_ratio": 1.1306048634984993,
   "addmm_over_gemm_ratio": 1.1571229289735574,
   "compiled_cudagraph_input_copy_us": 3115.476,
   "compile_error": null,
   "nocg_error": null,
   "forced_error": null,
   "clocks": {
    "gr_mhz": {
     "median": 1140.0,
     "min": 330.0,
     "max": 2070.0
    },
    "mem_mhz": {
     "median": 7001.0,
     "min": 5501.0,
     "max": 8001.0
    },
    "temp_c": {
     "median": 74.0,
     "min": 72.0,
     "max": 76.0
    },
    "power_w": {
     "median": 27.15,
     "min": 10.69,
     "max": 33.49
    },
    "n_samples": 39
   },
   "est_unfused_ms_adj": 22.923049636650834,
   "est_fused_ms_adj": 21.985961653757844,
   "estimated_gain_adj": 1.0426221057623297
  },
  {
   "name": "residual_M8192",
   "kind": "residual",
   "dims": {
    "M": 8192,
    "n": 16384,
    "k": 6144
   },
   "gemm_only_ms": 119.56811141967775,
   "unfused_ms": 123.6671371459961,
   "gemm_only_repeat_ms": 119.49753570556639,
   "gemm_drift_ratio": 0.9994097446779632,
   "best_unfused_ms": 123.6671371459961,
   "fused_paths": {
    "addmm_ms": 122.64777755737305,
    "compiled_ms": 128.99681854248047,
    "compiled_nocg_ms": 123.59233474731445,
    "compiled_forced_triton_ms": 119.52449417114258
   },
   "best_fused_ms": 119.52449417114258,
   "measured_gain": 1.0346593642046442,
   "measured_gain_verified": 1.0346593642046442,
   "est_unfused_ms": 94.25927228235294,
   "est_fused_ms": 89.522176,
   "estimated_gain": 1.0529153389027646,
   "fused_verified": false,
   "fused_verified_forced": true,
   "addmm_fused_verified": true,
   "addmm_kernel_evidence": [
    {
     "name": "void cutlass::Kernel2<cutlass_80_tensorop_bf16_s16816gemm_relu_bf16_256x128_32x3_nn_align8>(cutlass_80_tensorop_bf16_s16816gemm_relu_bf16_256x128_32x3_nn_align8::Params)",
     "count": 1,
     "total_us": 120661.737,
     "avg_us": 120661.737
    },
    {
     "name": "Memcpy DtoD (Device -> Device)",
     "count": 1,
     "total_us": 2617.081,
     "avg_us": 2617.081
    }
   ],
   "addmm_separate_kernels": [],
   "kernel_evidence": [
    {
     "name": "void cutlass::Kernel2<cutlass_80_tensorop_bf16_s16816gemm_relu_bf16_256x128_32x3_nn_align8>(cutlass_80_tensorop_bf16_s16816gemm_relu_bf16_256x128_32x3_nn_align8::Params)",
     "count": 1,
     "total_us": 119791.557,
     "avg_us": 119791.557
    },
    {
     "name": "void at::native::(anonymous namespace)::multi_tensor_apply_kernel<at::native::(anonymous namespace)::TensorListMetadata<2>, at::native::(anonymous namespace)::UnaryOpFunctor<c10::BFloat16, 2, 1, 1>, at::native::Copy<c10::BFloat16, c10::BFloat16> >(at::native::(anonymous namespace)::TensorListMetadata<2>, at::native::(anonymous namespace)::UnaryOpFunctor<c10::BFloat16, 2, 1, 1>, at::native::Copy<c10::BFloat16, c10::BFloat16>)",
     "count": 14,
     "total_us": 5982.082,
     "avg_us": 427.292
    },
    {
     "name": "Memcpy DtoD (Device -> Device)",
     "count": 1,
     "total_us": 2721.811,
     "avg_us": 2721.811
    }
   ],
   "fusion_evidence": {
    "n_kernels": 3,
    "dominant_kernel": "void cutlass::Kernel2<cutlass_80_tensorop_bf16_s16816gemm_relu_bf16_256x128_32x3_nn_align8>(cutlass_80_tensorop_bf16_s16816gemm_relu_bf16_256x128_32x3_nn_align8::Params)",
    "dominant_frac_of_gpu_time": 0.9323,
    "triton_gemm_template_present": false,
    "separate_elementwise_kernels": [],
    "vendor_fused_ok": true,
    "vendor_separate_kernels": []
   },
   "nocg_kernel_evidence": [
    {
     "name": "void cutlass::Kernel2<cutlass_80_tensorop_bf16_s16816gemm_relu_bf16_256x128_32x3_nn_align8>(cutlass_80_tensorop_bf16_s16816gemm_relu_bf16_256x128_32x3_nn_align8::Params)",
     "count": 1,
     "total_us": 119879.707,
     "avg_us": 119879.707
    },
    {
     "name": "Memcpy DtoD (Device -> Device)",
     "count": 1,
     "total_us": 3398.301,
     "avg_us": 3398.301
    }
   ],
   "nocg_fusion_evidence": {
    "n_kernels": 2,
    "dominant_kernel": "void cutlass::Kernel2<cutlass_80_tensorop_bf16_s16816gemm_relu_bf16_256x128_32x3_nn_align8>(cutlass_80_tensorop_bf16_s16816gemm_relu_bf16_256x128_32x3_nn_align8::Params)",
    "dominant_frac_of_gpu_time": 0.9724,
    "triton_gemm_template_present": false,
    "separate_elementwise_kernels": [],
    "vendor_fused_ok": true,
    "vendor_separate_kernels": []
   },
   "forced_kernel_evidence": [
    {
     "name": "triton_tem_fused_addmm_0",
     "count": 1,
     "total_us": 119103.402,
     "avg_us": 119103.402
    }
   ],
   "forced_fusion_evidence": {
    "n_kernels": 1,
    "dominant_kernel": "triton_tem_fused_addmm_0",
    "dominant_frac_of_gpu_time": 1.0,
    "triton_gemm_template_present": true,
    "separate_elementwise_kernels": [],
    "vendor_fused_ok": true,
    "vendor_separate_kernels": []
   },
   "numerics_ok": false,
   "max_abs_diff": 2.0,
   "nocg_numerics_ok": false,
   "nocg_max_abs_diff": 2.0,
   "forced_numerics_ok": false,
   "forced_max_abs_diff": 2.0,
   "addmm_numerics_ok": false,
   "addmm_max_abs_diff": 2.0,
   "compiled_over_gemm_ratio": 1.0788563690674051,
   "nocg_over_gemm_ratio": 1.033656325920478,
   "forced_over_gemm_ratio": 0.9996352100236653,
   "addmm_over_gemm_ratio": 1.0257565842692442,
   "compiled_cudagraph_input_copy_us": 5982.082,
   "compile_error": null,
   "nocg_error": null,
   "forced_error": null,
   "clocks": {
    "gr_mhz": {
     "median": 1140.0,
     "min": 255.0,
     "max": 2070.0
    },
    "mem_mhz": {
     "median": 7001.0,
     "min": 5501.0,
     "max": 8001.0
    },
    "temp_c": {
     "median": 75.0,
     "min": 72.0,
     "max": 76.0
    },
    "power_w": {
     "median": 24.515,
     "min": 10.8,
     "max": 37.09
    },
    "n_samples": 118
   },
   "est_unfused_ms_adj": 91.56362567143515,
   "est_fused_ms_adj": 87.8152737398632,
   "estimated_gain_adj": 1.04268451001674
  },
  {
   "name": "residual_glm_M2048",
   "kind": "residual",
   "dims": {
    "M": 2048,
    "n": 6144,
    "k": 16384
   },
   "gemm_only_ms": 29.771648406982425,
   "unfused_ms": 30.095759391784668,
   "gemm_only_repeat_ms": 29.788192749023438,
   "gemm_drift_ratio": 1.0005557079613077,
   "best_unfused_ms": 30.095759391784668,
   "fused_paths": {
    "addmm_ms": 29.920672416687015,
    "compiled_ms": 33.098302841186516,
    "compiled_nocg_ms": 30.11014461517334,
    "compiled_forced_triton_ms": 29.95255947113037
   },
   "best_fused_ms": 29.920672416687015,
   "measured_gain": 1.005851705892813,
   "measured_gain_verified": 1.005851705892813,
   "est_unfused_ms": 22.81372410980392,
   "est_fused_ms": 22.36962133333333,
   "estimated_gain": 1.0198529411764707,
   "fused_verified": false,
   "fused_verified_forced": true,
   "addmm_fused_verified": true,
   "addmm_kernel_evidence": [
    {
     "name": "ampere_bf16_s1688gemm_bf16_128x128_ldg8_f2f_stages_32x1_nn",
     "count": 1,
     "total_us": 29652.838,
     "avg_us": 29652.838
    },
    {
     "name": "Memcpy DtoD (Device -> Device)",
     "count": 1,
     "total_us": 153.273,
     "avg_us": 153.273
    },
    {
     "name": "Memset (Device)",
     "count": 1,
     "total_us": 1.249,
     "avg_us": 1.249
    }
   ],
   "addmm_separate_kernels": [],
   "kernel_evidence": [
    {
     "name": "ampere_bf16_s1688gemm_bf16_128x128_ldg8_f2f_stages_32x1_nn",
     "count": 1,
     "total_us": 29661.612,
     "avg_us": 29661.612
    },
    {
     "name": "void at::native::(anonymous namespace)::multi_tensor_apply_kernel<at::native::(anonymous namespace)::TensorListMetadata<2>, at::native::(anonymous namespace)::UnaryOpFunctor<c10::BFloat16, 2, 1, 1>, at::native::Copy<c10::BFloat16, c10::BFloat16> >(at::native::(anonymous namespace)::TensorListMetadata<2>, at::native::(anonymous namespace)::UnaryOpFunctor<c10::BFloat16, 2, 1, 1>, at::native::Copy<c10::BFloat16, c10::BFloat16>)",
     "count": 7,
     "total_us": 2587.998,
     "avg_us": 369.714
    },
    {
     "name": "Memcpy DtoD (Device -> Device)",
     "count": 1,
     "total_us": 279.292,
     "avg_us": 279.292
    },
    {
     "name": "Memset (Device)",
     "count": 1,
     "total_us": 1.825,
     "avg_us": 1.825
    }
   ],
   "fusion_evidence": {
    "n_kernels": 4,
    "dominant_kernel": "ampere_bf16_s1688gemm_bf16_128x128_ldg8_f2f_stages_32x1_nn",
    "dominant_frac_of_gpu_time": 0.9118,
    "triton_gemm_template_present": false,
    "separate_elementwise_kernels": [],
    "vendor_fused_ok": true,
    "vendor_separate_kernels": []
   },
   "nocg_kernel_evidence": [
    {
     "name": "ampere_bf16_s1688gemm_bf16_128x128_ldg8_f2f_stages_32x1_nn",
     "count": 1,
     "total_us": 29662.038,
     "avg_us": 29662.038
    },
    {
     "name": "Memcpy DtoD (Device -> Device)",
     "count": 1,
     "total_us": 177.87,
     "avg_us": 177.87
    },
    {
     "name": "Memset (Device)",
     "count": 1,
     "total_us": 2.433,
     "avg_us": 2.433
    }
   ],
   "nocg_fusion_evidence": {
    "n_kernels": 3,
    "dominant_kernel": "ampere_bf16_s1688gemm_bf16_128x128_ldg8_f2f_stages_32x1_nn",
    "dominant_frac_of_gpu_time": 0.994,
    "triton_gemm_template_present": false,
    "separate_elementwise_kernels": [],
    "vendor_fused_ok": true,
    "vendor_separate_kernels": []
   },
   "forced_kernel_evidence": [
    {
     "name": "triton_tem_fused_addmm_0",
     "count": 1,
     "total_us": 29699.976,
     "avg_us": 29699.976
    }
   ],
   "forced_fusion_evidence": {
    "n_kernels": 1,
    "dominant_kernel": "triton_tem_fused_addmm_0",
    "dominant_frac_of_gpu_time": 1.0,
    "triton_gemm_template_present": true,
    "separate_elementwise_kernels": [],
    "vendor_fused_ok": true,
    "vendor_separate_kernels": []
   },
   "numerics_ok": false,
   "max_abs_diff": 4.0,
   "nocg_numerics_ok": false,
   "nocg_max_abs_diff": 4.0,
   "forced_numerics_ok": false,
   "forced_max_abs_diff": 4.0,
   "addmm_numerics_ok": false,
   "addmm_max_abs_diff": 4.0,
   "compiled_over_gemm_ratio": 1.1117390071496305,
   "nocg_over_gemm_ratio": 1.0113697502927492,
   "forced_over_gemm_ratio": 1.0060766223514017,
   "addmm_over_gemm_ratio": 1.0050055679708227,
   "compiled_cudagraph_input_copy_us": 2587.998,
   "compile_error": null,
   "nocg_error": null,
   "forced_error": null,
   "clocks": {
    "gr_mhz": {
     "median": 1140.0,
     "min": 270.0,
     "max": 2070.0
    },
    "mem_mhz": {
     "median": 7001.0,
     "min": 810.0,
     "max": 8001.0
    },
    "temp_c": {
     "median": 75.0,
     "min": 72.0,
     "max": 77.0
    },
    "power_w": {
     "median": 27.59,
     "min": 11.3,
     "max": 37.04
    },
    "n_samples": 39
   },
   "est_unfused_ms_adj": 22.294512022286657,
   "est_fused_ms_adj": 21.943104028701786,
   "estimated_gain_adj": 1.0160145070234925
  },
  {
   "name": "residual_glm_M8192",
   "kind": "residual",
   "dims": {
    "M": 8192,
    "n": 6144,
    "k": 16384
   },
   "gemm_only_ms": 118.89649581909178,
   "unfused_ms": 120.90358352661133,
   "gemm_only_repeat_ms": 118.80369567871094,
   "gemm_drift_ratio": 0.9992194880114714,
   "best_unfused_ms": 120.90358352661133,
   "fused_paths": {
    "addmm_ms": 120.05039978027344,
    "compiled_ms": 128.1417236328125,
    "compiled_nocg_ms": 120.327823638916,
    "compiled_forced_triton_ms": 119.07627487182617
   },
   "best_fused_ms": 119.07627487182617,
   "measured_gain": 1.0153456988535463,
   "measured_gain_verified": 1.0153456988535463,
   "est_unfused_ms": 91.25489643921568,
   "est_fused_ms": 89.47848533333332,
   "estimated_gain": 1.0198529411764707,
   "fused_verified": false,
   "fused_verified_forced": true,
   "addmm_fused_verified": true,
   "addmm_kernel_evidence": [
    {
     "name": "ampere_bf16_s1688gemm_bf16_128x128_ldg8_f2f_stages_32x1_nn",
     "count": 1,
     "total_us": 119021.911,
     "avg_us": 119021.911
    },
    {
     "name": "Memcpy DtoD (Device -> Device)",
     "count": 1,
     "total_us": 1382.109,
     "avg_us": 1382.109
    },
    {
     "name": "Memset (Device)",
     "count": 1,
     "total_us": 3.2,
     "avg_us": 3.2
    }
   ],
   "addmm_separate_kernels": [],
   "kernel_evidence": [
    {
     "name": "ampere_bf16_s1688gemm_bf16_128x128_ldg8_f2f_stages_32x1_nn",
     "count": 1,
     "total_us": 120521.09,
     "avg_us": 120521.09
    },
    {
     "name": "void at::native::(anonymous namespace)::multi_tensor_apply_kernel<at::native::(anonymous namespace)::TensorListMetadata<2>, at::native::(anonymous namespace)::UnaryOpFunctor<c10::BFloat16, 2, 1, 1>, at::native::Copy<c10::BFloat16, c10::BFloat16> >(at::native::(anonymous namespace)::TensorListMetadata<2>, at::native::(anonymous namespace)::UnaryOpFunctor<c10::BFloat16, 2, 1, 1>, at::native::Copy<c10::BFloat16, c10::BFloat16>)",
     "count": 14,
     "total_us": 7653.357,
     "avg_us": 546.668
    },
    {
     "name": "Memcpy DtoD (Device -> Device)",
     "count": 1,
     "total_us": 1309.746,
     "avg_us": 1309.746
    },
    {
     "name": "Memset (Device)",
     "count": 1,
     "total_us": 2.143,
     "avg_us": 2.143
    }
   ],
   "fusion_evidence": {
    "n_kernels": 4,
    "dominant_kernel": "ampere_bf16_s1688gemm_bf16_128x128_ldg8_f2f_stages_32x1_nn",
    "dominant_frac_of_gpu_time": 0.9308,
    "triton_gemm_template_present": false,
    "separate_elementwise_kernels": [],
    "vendor_fused_ok": true,
    "vendor_separate_kernels": []
   },
   "nocg_kernel_evidence": [
    {
     "name": "ampere_bf16_s1688gemm_bf16_128x128_ldg8_f2f_stages_32x1_nn",
     "count": 1,
     "total_us": 118587.907,
     "avg_us": 118587.907
    },
    {
     "name": "Memcpy DtoD (Device -> Device)",
     "count": 1,
     "total_us": 1204.094,
     "avg_us": 1204.094
    },
    {
     "name": "Memset (Device)",
     "count": 1,
     "total_us": 3.712,
     "avg_us": 3.712
    }
   ],
   "nocg_fusion_evidence": {
    "n_kernels": 3,
    "dominant_kernel": "ampere_bf16_s1688gemm_bf16_128x128_ldg8_f2f_stages_32x1_nn",
    "dominant_frac_of_gpu_time": 0.9899,
    "triton_gemm_template_present": false,
    "separate_elementwise_kernels": [],
    "vendor_fused_ok": true,
    "vendor_separate_kernels": []
   },
   "forced_kernel_evidence": [
    {
     "name": "triton_tem_fused_addmm_0",
     "count": 1,
     "total_us": 120605.268,
     "avg_us": 120605.268
    }
   ],
   "forced_fusion_evidence": {
    "n_kernels": 1,
    "dominant_kernel": "triton_tem_fused_addmm_0",
    "dominant_frac_of_gpu_time": 1.0,
    "triton_gemm_template_present": true,
    "separate_elementwise_kernels": [],
    "vendor_fused_ok": true,
    "vendor_separate_kernels": []
   },
   "numerics_ok": false,
   "max_abs_diff": 4.0,
   "nocg_numerics_ok": false,
   "nocg_max_abs_diff": 4.0,
   "forced_numerics_ok": false,
   "forced_max_abs_diff": 6.0,
   "addmm_numerics_ok": false,
   "addmm_max_abs_diff": 4.0,
   "compiled_over_gemm_ratio": 1.0777586231623504,
   "nocg_over_gemm_ratio": 1.012038435699586,
   "forced_over_gemm_ratio": 1.001512063509491,
   "addmm_over_gemm_ratio": 1.0097051132855706,
   "compiled_cudagraph_input_copy_us": 7653.357,
   "compile_error": null,
   "nocg_error": null,
   "forced_error": null,
   "clocks": {
    "gr_mhz": {
     "median": 1140.0,
     "min": 315.0,
     "max": 1905.0
    },
    "mem_mhz": {
     "median": 5501.0,
     "min": 5501.0,
     "max": 8001.0
    },
    "temp_c": {
     "median": 76.0,
     "min": 72.0,
     "max": 77.0
    },
    "power_w": {
     "median": 26.12,
     "min": 10.72,
     "max": 35.65
    },
    "n_samples": 117
   },
   "est_unfused_ms_adj": 89.17804808914663,
   "est_fused_ms_adj": 87.77241611480714,
   "estimated_gain_adj": 1.0160145070234925
  },
  {
   "name": "moe_E8",
   "kind": "swiglu",
   "dims": {
    "experts": 8,
    "tokens_per_expert": 128,
    "hidden": 2048,
    "inter": 2048
   },
   "gemm_only_ms": 1.198352038860321,
   "unfused_ms": 1.4522879719734194,
   "gemm_only_repeat_ms": 1.3076960444450378,
   "gemm_drift_ratio": 1.0912453119274592,
   "eager_rel_max_vs_fp32": 0.01597474329173565,
   "unfused_compiled_nocg_ms": 1.4325279593467712,
   "best_unfused_ms": 1.4325279593467712,
   "fused_paths": {
    "compiled_ms": 2.6966240406036377,
    "compiled_forced_triton_ms": 1.4710400104522705
   },
   "best_fused_ms": 1.4710400104522705,
   "measured_gain": 0.9872525299477845,
   "measured_gain_verified": null,
   "est_unfused_ms": 1.013366462745098,
   "est_fused_ms": 0.9393493333333333,
   "estimated_gain": 1.078796169630643,
   "fused_verified": false,
   "fused_verified_forced": false,
   "kernel_evidence": [
    {
     "name": "void at::native::(anonymous namespace)::multi_tensor_apply_kernel<at::native::(anonymous namespace)::TensorListMetadata<2>, at::native::(anonymous namespace)::UnaryOpFunctor<c10::BFloat16, 2, 1, 1>, at::native::Copy<c10::BFloat16, c10::BFloat16> >(at::native::(anonymous namespace)::TensorListMetadata<2>, at::native::(anonymous namespace)::UnaryOpFunctor<c10::BFloat16, 2, 1, 1>, at::native::Copy<c10::BFloat16, c10::BFloat16>)",
     "count": 4,
     "total_us": 1366.536,
     "avg_us": 341.634
    },
    {
     "name": "void cutlass::Kernel2<cutlass_80_tensorop_bf16_s16816gemm_relu_bf16_64x64_32x6_nn_align8>(cutlass_80_tensorop_bf16_s16816gemm_relu_bf16_64x64_32x6_nn_align8::Params)",
     "count": 1,
     "total_us": 1268.451,
     "avg_us": 1268.451
    },
    {
     "name": "triton_poi_fused_mul_silu_slice_0",
     "count": 1,
     "total_us": 39.477,
     "avg_us": 39.477
    }
   ],
   "fusion_evidence": {
    "n_kernels": 3,
    "dominant_kernel": "void at::native::(anonymous namespace)::multi_tensor_apply_kernel<at::native::(anonymous namespace)::TensorListMetadata<2>, at::native::(anonymous namespace)::UnaryOpFunctor<c10::BFloat16, 2, 1, 1>, at::native::Copy<c10::BFloat16, c10::BFloat16> >(at::native::(anonymous namespace)::TensorListMetadata<2>, at::native::(anonymous namespace)::UnaryOpFunctor<c10::BFloat16, 2, 1, 1>, at::native::Copy<c10::BFloat16, c10::BFloat16>)",
    "dominant_frac_of_gpu_time": 0.511,
    "triton_gemm_template_present": false,
    "separate_elementwise_kernels": [
     "triton_poi_fused_mul_silu_slice_0"
    ]
   },
   "nocg_kernel_evidence": [
    {
     "name": "void cutlass::Kernel2<cutlass_80_tensorop_bf16_s16816gemm_relu_bf16_64x64_32x6_nn_align8>(cutlass_80_tensorop_bf16_s16816gemm_relu_bf16_64x64_32x6_nn_align8::Params)",
     "count": 1,
     "total_us": 1268.367,
     "avg_us": 1268.367
    },
    {
     "name": "triton_poi_fused_mul_silu_slice_0",
     "count": 1,
     "total_us": 48.16,
     "avg_us": 48.16
    }
   ],
   "nocg_fusion_evidence": {
    "n_kernels": 2,
    "dominant_kernel": "void cutlass::Kernel2<cutlass_80_tensorop_bf16_s16816gemm_relu_bf16_64x64_32x6_nn_align8>(cutlass_80_tensorop_bf16_s16816gemm_relu_bf16_64x64_32x6_nn_align8::Params)",
    "dominant_frac_of_gpu_time": 0.9634,
    "triton_gemm_template_present": false,
    "separate_elementwise_kernels": [
     "triton_poi_fused_mul_silu_slice_0"
    ]
   },
   "forced_kernel_evidence": [
    {
     "name": "triton_tem_fused_bmm_0",
     "count": 1,
     "total_us": 1329.088,
     "avg_us": 1329.088
    },
    {
     "name": "triton_poi_fused_mul_silu_slice_1",
     "count": 1,
     "total_us": 46.153,
     "avg_us": 46.153
    }
   ],
   "forced_fusion_evidence": {
    "n_kernels": 2,
    "dominant_kernel": "triton_tem_fused_bmm_0",
    "dominant_frac_of_gpu_time": 0.9664,
    "triton_gemm_template_present": true,
    "separate_elementwise_kernels": [
     "triton_poi_fused_mul_silu_slice_1"
    ]
   },
   "numerics_ok": true,
   "max_abs_diff": 8.0,
   "nocg_numerics_ok": true,
   "nocg_max_abs_diff": 8.0,
   "forced_numerics_ok": true,
   "forced_max_abs_diff": 8.0,
   "compiled_over_gemm_ratio": 2.250277008055355,
   "nocg_over_gemm_ratio": 1.1954149639609748,
   "forced_over_gemm_ratio": 1.2275524743557713,
   "triton_over_gemm_ratio": null,
   "compiled_cudagraph_input_copy_us": 1366.536,
   "triton_info": {},
   "compile_error": null,
   "nocg_error": null,
   "forced_error": null,
   "clocks": {
    "gr_mhz": {
     "median": 1125.0,
     "min": 285.0,
     "max": 2070.0
    },
    "mem_mhz": {
     "median": 5501.0,
     "min": 5501.0,
     "max": 8001.0
    },
    "temp_c": {
     "median": 73.0,
     "min": 72.0,
     "max": 74.0
    },
    "power_w": {
     "median": 17.04,
     "min": 10.99,
     "max": 36.65
    },
    "n_samples": 21
   },
   "est_unfused_ms_adj": 0.9800069376360626,
   "est_fused_ms_adj": 0.9214389387052507,
   "estimated_gain_adj": 1.0635614542327765
  },
  {
   "name": "moe_E32",
   "kind": "swiglu",
   "dims": {
    "experts": 32,
    "tokens_per_expert": 128,
    "hidden": 2048,
    "inter": 2048
   },
   "gemm_only_ms": 4.39900803565979,
   "unfused_ms": 5.645264148712158,
   "gemm_only_repeat_ms": 5.612367868423462,
   "gemm_drift_ratio": 1.2758257822963228,
   "eager_rel_max_vs_fp32": 0.01613393984735012,
   "unfused_compiled_nocg_ms": 8.605888366699219,
   "best_unfused_ms": 5.645264148712158,
   "fused_paths": {
    "compiled_ms": 11.273215770721434,
    "compiled_forced_triton_ms": 6.979632139205933
   },
   "best_fused_ms": 6.979632139205933,
   "measured_gain": 0.8088197251831692,
   "measured_gain_verified": null,
   "est_unfused_ms": 4.031620517647059,
   "est_fused_ms": 3.735552,
   "estimated_gain": 1.0792569659442723,
   "fused_verified": false,
   "fused_verified_forced": false,
   "kernel_evidence": [
    {
     "name": "void at::native::(anonymous namespace)::multi_tensor_apply_kernel<at::native::(anonymous namespace)::TensorListMetadata<2>, at::native::(anonymous namespace)::UnaryOpFunctor<c10::BFloat16, 2, 1, 1>, at::native::Copy<c10::BFloat16, c10::BFloat16> >(at::native::(anonymous namespace)::TensorListMetadata<2>, at::native::(anonymous namespace)::UnaryOpFunctor<c10::BFloat16, 2, 1, 1>, at::native::Copy<c10::BFloat16, c10::BFloat16>)",
     "count": 14,
     "total_us": 5818.57,
     "avg_us": 415.612
    },
    {
     "name": "void cutlass::Kernel2<cutlass_80_tensorop_bf16_s16816gemm_relu_bf16_64x64_32x6_nn_align8>(cutlass_80_tensorop_bf16_s16816gemm_relu_bf16_64x64_32x6_nn_align8::Params)",
     "count": 1,
     "total_us": 5028.762,
     "avg_us": 5028.762
    },
    {
     "name": "triton_poi_fused_mul_silu_slice_0",
     "count": 1,
     "total_us": 185.697,
     "avg_us": 185.697
    }
   ],
   "fusion_evidence": {
    "n_kernels": 3,
    "dominant_kernel": "void at::native::(anonymous namespace)::multi_tensor_apply_kernel<at::native::(anonymous namespace)::TensorListMetadata<2>, at::native::(anonymous namespace)::UnaryOpFunctor<c10::BFloat16, 2, 1, 1>, at::native::Copy<c10::BFloat16, c10::BFloat16> >(at::native::(anonymous namespace)::TensorListMetadata<2>, at::native::(anonymous namespace)::UnaryOpFunctor<c10::BFloat16, 2, 1, 1>, at::native::Copy<c10::BFloat16, c10::BFloat16>)",
    "dominant_frac_of_gpu_time": 0.5274,
    "triton_gemm_template_present": false,
    "separate_elementwise_kernels": [
     "triton_poi_fused_mul_silu_slice_0"
    ]
   },
   "nocg_kernel_evidence": [
    {
     "name": "void cutlass::Kernel2<cutlass_80_tensorop_bf16_s16816gemm_relu_bf16_64x64_32x6_nn_align8>(cutlass_80_tensorop_bf16_s16816gemm_relu_bf16_64x64_32x6_nn_align8::Params)",
     "count": 1,
     "total_us": 8038.925,
     "avg_us": 8038.925
    },
    {
     "name": "triton_poi_fused_mul_silu_slice_0",
     "count": 1,
     "total_us": 228.481,
     "avg_us": 228.481
    }
   ],
   "nocg_fusion_evidence": {
    "n_kernels": 2,
    "dominant_kernel": "void cutlass::Kernel2<cutlass_80_tensorop_bf16_s16816gemm_relu_bf16_64x64_32x6_nn_align8>(cutlass_80_tensorop_bf16_s16816gemm_relu_bf16_64x64_32x6_nn_align8::Params)",
    "dominant_frac_of_gpu_time": 0.9724,
    "triton_gemm_template_present": false,
    "separate_elementwise_kernels": [
     "triton_poi_fused_mul_silu_slice_0"
    ]
   },
   "forced_kernel_evidence": [
    {
     "name": "triton_tem_fused_bmm_0",
     "count": 1,
     "total_us": 6581.779,
     "avg_us": 6581.779
    },
    {
     "name": "triton_poi_fused_mul_silu_slice_1",
     "count": 1,
     "total_us": 179.126,
     "avg_us": 179.126
    }
   ],
   "forced_fusion_evidence": {
    "n_kernels": 2,
    "dominant_kernel": "triton_tem_fused_bmm_0",
    "dominant_frac_of_gpu_time": 0.9735,
    "triton_gemm_template_present": true,
    "separate_elementwise_kernels": [
     "triton_poi_fused_mul_silu_slice_1"
    ]
   },
   "numerics_ok": true,
   "max_abs_diff": 16.0,
   "nocg_numerics_ok": true,
   "nocg_max_abs_diff": 16.0,
   "forced_numerics_ok": true,
   "forced_max_abs_diff": 16.0,
   "compiled_over_gemm_ratio": 2.56267223868133,
   "nocg_over_gemm_ratio": 1.9563247661602543,
   "forced_over_gemm_ratio": 1.5866377334678101,
   "triton_over_gemm_ratio": null,
   "compiled_cudagraph_input_copy_us": 5818.57,
   "triton_info": {},
   "compile_error": null,
   "nocg_error": null,
   "forced_error": null,
   "clocks": {
    "gr_mhz": {
     "median": 1222.5,
     "min": 405.0,
     "max": 2070.0
    },
    "mem_mhz": {
     "median": 7001.0,
     "min": 5501.0,
     "max": 8001.0
    },
    "temp_c": {
     "median": 74.0,
     "min": 72.0,
     "max": 75.0
    },
    "power_w": {
     "median": 26.59,
     "min": 10.96,
     "max": 32.76
    },
    "n_samples": 18
   },
   "est_unfused_ms_adj": 3.8985989380162214,
   "est_fused_ms_adj": 3.6643269422929734,
   "estimated_gain_adj": 1.0639331586434946
  }
 ],
 "annotations_post_hoc": {
  "note": "Added after the run during analysis/review (2026-07-21). residual_numerics uses FRESH seed-0 tensors at the same dims (not the run's exact tensors): the strict allclose numerics_ok=false flags on residual rows are false alarms -- addmm/fused paths round once where eager mm+add rounds twice; values differ by <=1 bf16 ulp and the fused paths are closer to the fp32 reference than eager is. derived_late_phase gives drift-robust within-late-phase gains (both operands measured after the compile/autotune phase) and *_over_gemm_repeat re-references fused kernels to the CONTEMPORANEOUS end-of-config GEMM. swiglu_M2048_h1024 is flagged baseline_unmeasurable (unfused_ms < gemm_only_ms, impossible at steady clock).",
  "residual_numerics": {
   "residual_M2048": {
    "eager_rel_max_vs_fp32": 0.01182724442332983,
    "addmm_rel_max_vs_fp32": 0.0038881050422787666,
    "addmm_vs_eager_max_abs": 2.0,
    "frac_within_1ulp": 0.9984235763549805
   },
   "residual_M8192": {
    "eager_rel_max_vs_fp32": 0.014598114416003227,
    "addmm_rel_max_vs_fp32": 0.0038837455213069916,
    "addmm_vs_eager_max_abs": 2.0,
    "frac_within_1ulp": 0.9984045028686523
   },
   "residual_glm_M2048": {
    "eager_rel_max_vs_fp32": 1.3064361810684204,
    "addmm_rel_max_vs_fp32": 1.0744327306747437,
    "addmm_vs_eager_max_abs": 4.0,
    "frac_within_1ulp": 0.879799485206604
   },
   "residual_glm_M8192": {
    "eager_rel_max_vs_fp32": 1.2307742834091187,
    "addmm_rel_max_vs_fp32": 1.3529458045959473,
    "addmm_vs_eager_max_abs": 4.0,
    "frac_within_1ulp": 0.8799104690551758
   }
  },
  "derived_late_phase": {
   "swiglu_M2048_h1024": {
    "late_phase_gain_nocg_over_triton": 1.0595519303272378,
    "triton_over_gemm_repeat": 1.0900716906883465,
    "drift": 0.8598502222996176,
    "baseline_unmeasurable": true
   },
   "swiglu_M2048_h2048": {
    "late_phase_gain_nocg_over_triton": 1.0456401203085348,
    "triton_over_gemm_repeat": 1.0751921793161998,
    "drift": 0.8715360770948137
   },
   "swiglu_M2048_h4096": {
    "late_phase_gain_nocg_over_triton": 1.0557005494528227,
    "triton_over_gemm_repeat": 0.9887250297682881,
    "drift": 1.0015881421863342
   },
   "swiglu_M8192_h1024": {
    "late_phase_gain_nocg_over_triton": 1.0738774539374614,
    "triton_over_gemm_repeat": 0.9800687755090949,
    "drift": 1.01381787188543
   },
   "swiglu_M8192_h2048": {
    "late_phase_gain_nocg_over_triton": 0.8900428169187625,
    "triton_over_gemm_repeat": 1.0057189652799563,
    "drift": 1.34526200791347
   },
   "swiglu_M8192_h4096": {
    "late_phase_gain_nocg_over_triton": 0.9397949334875566,
    "triton_over_gemm_repeat": 1.046650328279197,
    "drift": 1.2341800163877972
   },
   "residual_M2048": {
    "late_phase_gain_nocg_over_forced": 1.0285678225445374,
    "forced_over_gemm_repeat": 0.9955253711674565,
    "drift": 1.1356866396811511
   },
   "residual_M8192": {
    "late_phase_gain_nocg_over_forced": 1.0340335309877764,
    "forced_over_gemm_repeat": 1.0002255985064212,
    "drift": 0.9994097446779632
   },
   "residual_glm_M2048": {
    "late_phase_gain_nocg_over_forced": 1.0052611578718291,
    "forced_over_gemm_repeat": 1.005517848077988,
    "drift": 1.0005557079613077
   },
   "residual_glm_M8192": {
    "late_phase_gain_nocg_over_forced": 1.0105104796773077,
    "forced_over_gemm_repeat": 1.0022943662784058,
    "drift": 0.9992194880114714
   },
   "moe_E8": {
    "late_phase_gain_nocg_over_triton": null,
    "triton_over_gemm_repeat": null,
    "drift": 1.0912453119274592
   },
   "moe_E32": {
    "late_phase_gain_nocg_over_triton": null,
    "triton_over_gemm_repeat": null,
    "drift": 1.2758257822963228
   }
  },
  "aggregates": {
   "clean5": {
    "configs": [
     "swiglu_M2048_h4096",
     "swiglu_M8192_h1024",
     "residual_M8192",
     "residual_glm_M2048",
     "residual_glm_M8192"
    ],
    "gm_meas_ver": 1.0367836767498197,
    "gm_est_stock": 1.0569382076380593,
    "gm_est_adj": 1.0461048122019638
   },
   "all_with_verified_path_n10": {
    "configs": [
     "swiglu_M2048_h1024",
     "swiglu_M2048_h2048",
     "swiglu_M2048_h4096",
     "swiglu_M8192_h1024",
     "swiglu_M8192_h2048",
     "swiglu_M8192_h4096",
     "residual_M2048",
     "residual_M8192",
     "residual_glm_M2048",
     "residual_glm_M8192"
    ],
    "gm_meas_ver": 0.9825448145591502
   },
   "nonthrottled_n7": {
    "configs": [
     "swiglu_M2048_h1024",
     "swiglu_M2048_h2048",
     "swiglu_M2048_h4096",
     "swiglu_M8192_h1024",
     "residual_M8192",
     "residual_glm_M2048",
     "residual_glm_M8192"
    ],
    "gm_meas_ver": 1.0138623283029646,
    "gm_est_adj": 1.0598148018770108
   },
   "delivered_fraction_clean": {
    "swiglu_M2048_h4096": 1.7424619910748167,
    "swiglu_M8192_h1024": 0.5777710307527468,
    "residual_M8192": 0.8119892717768483,
    "residual_glm_M2048": 0.3654003138672176,
    "residual_glm_M8192": 0.9582373551077732
   },
   "compiled_default_vs_eager_wins": 2,
   "compiled_default_vs_best_unfused_wins": 1,
   "forced_over_gemm_range": [
    0.9593605912567906,
    1.5936404723814246
   ],
   "all12_c500_convention_gm_measured_gain": 0.9917414203236209,
   "clean5_plus_positive_drift_tainted_n7": {
    "configs": [
     "swiglu_M2048_h4096",
     "swiglu_M8192_h1024",
     "residual_M8192",
     "residual_glm_M2048",
     "residual_glm_M8192",
     "swiglu_M2048_h2048",
     "residual_M2048"
    ],
    "note": "clean5 + the two drift-excluded rows that carried POSITIVE verified gains (swiglu_M2048_h2048 drift 0.87, residual_M2048 drift 1.14); the honest \"include the tainted-but-plausible evidence\" sensitivity",
    "gm_meas_ver": 1.0378972177148806,
    "gm_est_adj": 1.0480815451649468
   },
   "nonthrottled_n7_note": "CAUTION: this set includes swiglu_M2048_h1024 (baseline unmeasurable, mv 0.879) \u2014 it is the drift<1.05 cut, not a usable-evidence cut"
  }
 }
}